adaptivegears/__init__.py
adaptivegears/cli.py
adaptivegears/aws/__init__.py
adaptivegears/aws/cli.py
adaptivegears/aws/cloudwatch.py
adaptivegears/aws/compute.py
adaptivegears/aws/region.py
adaptivegears/aws/units.py
adaptivegears/aws/pricing/__init__.py
adaptivegears/aws/pricing/offers.py
adaptivegears/aws/pricing/price.py
adaptivegears/pg/__init__.py
adaptivegears/pg/cli.py
adaptivegears/pg/histogram.py
adaptivegears/pg/schema.py
adaptivegears/tags/__init__.py
adaptivegears/tags/cli.py
adaptivegears/tags/exports.py
adaptivegears/tags/imports.py
adaptivegears/tags/tags.py
adaptivegears/util/__init__.py
adaptivegears/util/cli.py
adaptivegears-0.4.2.dist-info/METADATA
adaptivegears-0.4.2.dist-info/WHEEL
adaptivegears-0.4.2.dist-info/entry_points.txt
adaptivegears-0.4.2.dist-info/licenses/LICENSE
adaptivegears-0.4.2.dist-info/RECORD
