Metadata-Version: 2.4
Name: adaptivegears
Version: 0.4.2
Summary: CLI tools for data engineering workflows
Author: Andrey Gubarev
License:                                  Apache License
License-File: LICENSE
Requires-Python: >=3.13
Requires-Dist: boto3>=1.35
Requires-Dist: joblib>=1.4
Requires-Dist: openpyxl>=3.1
Requires-Dist: pandas>=2.0
Requires-Dist: psycopg[binary]>=3.2
Requires-Dist: pydantic>=2.0
Requires-Dist: typer>=0.15
